.VERSION
AUTHORS.rst
CONTRIBUTING.rst
HISTORY.rst
LICENSE
MANIFEST.in
Pipfile
Pipfile.lock
README.rst
USAGE.rst
azure_energy_labeler_cli.py
dev-requirements.txt
requirements.txt
setup.cfg
setup.py
azureenergylabelercli/.VERSION
azureenergylabelercli/AUTHORS.rst
azureenergylabelercli/CONTRIBUTING.rst
azureenergylabelercli/HISTORY.rst
azureenergylabelercli/LICENSE
azureenergylabelercli/Pipfile
azureenergylabelercli/Pipfile.lock
azureenergylabelercli/README.rst
azureenergylabelercli/USAGE.rst
azureenergylabelercli/__init__.py
azureenergylabelercli/_version.py
azureenergylabelercli/azureenergylabelercli.py
azureenergylabelercli/azureenergylabelercliexceptions.py
azureenergylabelercli/dev-requirements.txt
azureenergylabelercli/requirements.txt
azureenergylabelercli/validators.py
azureenergylabelercli.egg-info/PKG-INFO
azureenergylabelercli.egg-info/SOURCES.txt
azureenergylabelercli.egg-info/dependency_links.txt
azureenergylabelercli.egg-info/entry_points.txt
azureenergylabelercli.egg-info/not-zip-safe
azureenergylabelercli.egg-info/requires.txt
azureenergylabelercli.egg-info/top_level.txt
azureenergylabelercli/conf/logging.json-example
docs/Makefile
docs/authors.rst
docs/conf.py
docs/contributing.rst
docs/history.rst
docs/index.rst
docs/installation.rst
docs/readme.rst
docs/usage.rst
tests/test_azureenergylabelercli.py