Metadata-Version: 2.1
Name: azureenergylabelercli
Version: 2.0.2
Summary: A cli to help generate energy label for Azure tenant, subscriptions and resource groups.
Home-page: https://github.com/schubergphilis/azureenergylabelercli
Author: Sayantan Khanra
Author-email: skhanra@schubergphilis.com
License: MIT
Keywords: azureenergylabelercli
Classifier: Development Status :: 1 - Planning
Classifier: Intended Audience :: Developers
Classifier: License :: OSI Approved :: MIT License
Classifier: Natural Language :: English
Classifier: Programming Language :: Python :: 3.7
License-File: LICENSE
License-File: AUTHORS.rst
